vizro_ai/__init__.py
vizro_ai/agents/__init__.py
vizro_ai/agents/_chart_agent.py
vizro_ai/agents/_utils/__init__.py
vizro_ai/agents/_utils/_constants.py
vizro_ai/agents/_utils/_safeguard.py
vizro_ai/agents/response_models/__init__.py
vizro_ai/agents/response_models/_response_models.py
vizro_ai-0.4.0.dist-info/METADATA
vizro_ai-0.4.0.dist-info/WHEEL
vizro_ai-0.4.0.dist-info/licenses/LICENSE.txt
vizro_ai-0.4.0.dist-info/RECORD
