Metadata-Version: 2.4
Name: vizro_ai
Version: 0.4.0
Summary: Vizro-AI provides pre-configured agents that help with data visualizations
Author: Vizro Team
License-File: LICENSE.txt
Classifier: Programming Language :: Python
Classifier: Programming Language :: Python :: 3.10
Classifier: Programming Language :: Python :: 3.11
Classifier: Programming Language :: Python :: 3.12
Classifier: Programming Language :: Python :: 3.13
Classifier: Programming Language :: Python :: 3.14
Requires-Python: >=3.10
Requires-Dist: autoflake
Requires-Dist: black
Requires-Dist: pandas
Requires-Dist: plotly
Requires-Dist: pydantic-ai-slim>=1.39.0
Provides-Extra: anthropic
Requires-Dist: pydantic-ai-slim[anthropic]; extra == 'anthropic'
Provides-Extra: google
Requires-Dist: pydantic-ai-slim[google]; extra == 'google'
Provides-Extra: mistral
Requires-Dist: pydantic-ai-slim[mistral]; extra == 'mistral'
Provides-Extra: openai
Requires-Dist: pydantic-ai-slim[openai]; extra == 'openai'
